becquerel/__init__.py
becquerel/__metadata__.py
becquerel/core/__init__.py
becquerel/core/autocal.py
becquerel/core/calibration.py
becquerel/core/energycal.py
becquerel/core/fitting.py
becquerel/core/peakfinder.py
becquerel/core/plotting.py
becquerel/core/rebin.py
becquerel/core/spectrum.py
becquerel/core/utils.py
becquerel/io/__init__.py
becquerel/io/h5.py
becquerel/parsers/__init__.py
becquerel/parsers/cnf.py
becquerel/parsers/h5.py
becquerel/parsers/iec1455.py
becquerel/parsers/parsers.py
becquerel/parsers/spc.py
becquerel/parsers/spe.py
becquerel/tools/__init__.py
becquerel/tools/_nndc_dummy_text.py
becquerel/tools/df_cache.py
becquerel/tools/element.py
becquerel/tools/isotope.py
becquerel/tools/isotope_qty.py
becquerel/tools/materials.py
becquerel/tools/materials_compendium.py
becquerel/tools/materials_error.py
becquerel/tools/materials_nist.py
becquerel/tools/nndc.py
becquerel/tools/wallet_cache.py
becquerel/tools/xcom.py
becquerel-0.7.0.dist-info/licenses/LICENSE.txt
becquerel-0.7.0.dist-info/METADATA
becquerel-0.7.0.dist-info/WHEEL
becquerel-0.7.0.dist-info/top_level.txt
becquerel-0.7.0.dist-info/RECORD
