Metadata-Version: 2.4
Name: becquerel
Version: 0.7.0
Summary: Tools for radiation spectral analysis.
Home-page: https://github.com/lbl-anp/becquerel
Download-URL: https://github.com/lbl-anp/becquerel/releases
Maintainer: The Becquerel Development Team
Maintainer-email: becquerel-dev@lbl.gov
License: Other/Proprietary License (see LICENSE.txt)
Platform: any
Classifier: Development Status :: 4 - Beta
Classifier: Intended Audience :: Science/Research
Classifier: License :: Other/Proprietary License
Classifier: Operating System :: OS Independent
Classifier: Programming Language :: Python
Classifier: Programming Language :: Python :: 3
Classifier: Programming Language :: Python :: 3 :: Only
Classifier: Programming Language :: Python :: 3.9
Classifier: Programming Language :: Python :: 3.10
Classifier: Programming Language :: Python :: 3.11
Classifier: Programming Language :: Python :: 3.12
Classifier: Programming Language :: Python :: 3.13
Classifier: Topic :: Scientific/Engineering
Classifier: Topic :: Scientific/Engineering :: Physics
Requires-Python: >=3.6
License-File: LICENSE.txt
Requires-Dist: asteval
Requires-Dist: beautifulsoup4
Requires-Dist: black>=22.3.0
Requires-Dist: h5py
Requires-Dist: html5lib
Requires-Dist: iminuit
Requires-Dist: llvmlite
Requires-Dist: lmfit
Requires-Dist: lxml
Requires-Dist: matplotlib
Requires-Dist: numba>=0.47.0
Requires-Dist: numdifftools
Requires-Dist: numpy
Requires-Dist: pandas
Requires-Dist: python-dateutil
Requires-Dist: requests
Requires-Dist: scipy
Requires-Dist: setuptools
Requires-Dist: uncertainties>=3.0.3
Dynamic: classifier
Dynamic: description
Dynamic: description-content-type
Dynamic: download-url
Dynamic: home-page
Dynamic: license
Dynamic: license-file
Dynamic: maintainer
Dynamic: maintainer-email
Dynamic: platform
Dynamic: requires-dist
Dynamic: requires-python
Dynamic: summary
